task4/control_path.v
// Имена новых управляющих портов добавить после соответствующего комментария в первой строке объявления модуля.
// Сами объявления дописывать под соответствующим комментарием после имеющихся объявлений портов. Комментарий не стирать.
// Реализацию управляющего автомата дописывать под соответствующим комментарием в конце модуля. Комментарий не стирать.
// По необходимости можно раскомментировать ключевые слова "reg" в объявлениях портов.
module control_path(on, start, regime, active, y_select_next, s_step, y_en, s_en, y_store_x, s_add, s_zero, clk, rst, s_is_zero);
  input [1:0] on;
  input start, clk, rst;
  output reg [1:0] regime;
  output reg active;
  output reg [1:0] y_select_next;
  output reg  [1:0] s_step;
  output reg  y_en;
  output reg  s_en;
  output reg y_store_x; // ну тут не так необходимо, но пусть все выглядит одинаково
  output reg  s_add;
  output reg  s_zero;
  
  /* ОБЪЯВЛЕНИЯ НОВЫХ УПРАВЛЯЮЩИХ ПОРТОВ */
  
  input s_is_zero;
  
  
  /* КОД УПРАВЛЯЮЩЕГО АВТОМАТА */
  
  // локальные точки 
  reg [4:0] counter16; 
  reg [1:0] counter3;
  
  wire enum_off;
  wire refresh_off;
  assign enum_off = (counter16 == 1'b0);
  assign refresh_off = (counter3 == 1'b0);
  
  // состояние автомата управляющего выходами regime и active  
  localparam STATE_OFF = 3'd0,
             STATE_ENUM_INACTIV = 3'd1,
             STATE_ENUM_ACTIV = 3'd2,
             STATE_COUNT = 3'd3,
             STATE_REFRESH = 3'd4;

  reg [2:0] state, next_state; 
             
  always @(posedge clk, posedge rst)
    if (rst) state <= STATE_OFF;
    else state <= next_state;
	
  //процедура функции переходов Sigma_T
  always @* begin 
    next_state = 1'bx;
    
    case(state)
    STATE_OFF: case (on)
               2'd0: next_state = STATE_OFF;
               2'd1: next_state = STATE_ENUM_INACTIV;
               2'd2: next_state = STATE_COUNT;
               2'd3: next_state = STATE_REFRESH;
               endcase
               
    STATE_ENUM_INACTIV: if (start) next_state = STATE_ENUM_ACTIV;
                        else next_state = STATE_ENUM_INACTIV;
    
    STATE_ENUM_ACTIV:   if (enum_off) next_state = STATE_OFF;
                        else next_state = STATE_ENUM_ACTIV;
    
    STATE_COUNT:  if (start) next_state = STATE_COUNT;
                  else next_state = STATE_OFF;
                  
    STATE_REFRESH: if (refresh_off) next_state = STATE_OFF;
                   else next_state = STATE_REFRESH;
    endcase    
  end
  
  
  //процедура функции выходов Sigma_В
  
  always @* begin 
    regime = 1'bx; active = 1'bx;
    
    case(state)
    STATE_OFF:  begin
                  regime = 2'd0;
                  active = 0;
                end
               
    STATE_ENUM_INACTIV: begin
                          regime = 2'd1;
                          active = 0;
                        end
    
    STATE_ENUM_ACTIV:   begin
                          regime = 2'd1;
                          active = 1;
                        end
    
    STATE_COUNT:  begin
                    regime = 2'd2;
                    active = 0;
                  end
                  
    STATE_REFRESH:  begin
                      regime = 2'd3;
                      active = 0;
                    end
    endcase    
  end
  

  //процедура для counter16
  always @(posedge clk)
    if (state == STATE_ENUM_ACTIV) counter16 <= counter16 - 1; 
    else counter16 <= 5'd16;  
    
  //процедура для counter3
  always @(posedge clk)
    if (state == STATE_REFRESH) counter3 <= counter3 - 1; 
    else counter3 <= 2'd2;


  // типовые реализации закончились, можно отжигать (?)
  
  
  
  // управляющие выходы для  операционного автомата 
  
  //процедуры для каждого состояния  
  always @* 
    if (state == STATE_OFF) begin
      y_en = 0;
      s_en = 0;
    end
  
  always @* begin 
    if (state == STATE_ENUM_ACTIV) begin
      y_en = 0;
      s_en = 0;
      s_add = 1;
      case (counter16)
      5'd16: begin
        s_step = 2'd1; 
        s_zero = 1;
        s_en = 1;
      end
      5'd12: begin
        s_en = 1;
        s_step = 2'd2;
        s_zero = 0;
      end
      5'd8: begin
        s_en = 1;
      end
      5'd4: begin
        s_en = 1;
      end
      5'd0: begin
        s_en = 1;
        s_zero = 1;
        s_step = 1;
      end
      endcase
    end
  end
  
  
  always @* 
    if (state == STATE_COUNT) 
      if (start)
        begin
        y_store_x = 0;
        s_step = 2'd1;
        s_en = 1;
        s_add = 0;
        s_zero=0;
        if (s_is_zero) begin 
          y_en = 1;
          y_select_next = 2'd1;
        end
        else
          y_en = 0 ;
        end
      else begin
        s_en = 0;
        y_en = 0;
      end
    
  always @* 
    if (state == STATE_REFRESH)
      case (counter3) 
      2'd2: begin
        y_en=1;
        s_en=0;
        y_store_x = 1;
      end
      2'd1: begin
        s_en = 1;
        s_step = 1;
        s_add = 1;
        y_en = 1;
        y_store_x = 0 ;
        y_select_next = 2'd3; 
      end
      2'd0: begin
        y_en =0;
        s_en = 0;
      end
      endcase
    
  
endmodule

task4/data_path.v
// Новые порты и точки объявлять в начале модуля под соответствующим комментарием. Комментарий не стирать.
// Имена новых портов записать вместо соответствующего комментария в начале объявления модуля.
// Новые подсхемы дописывать в конце модуля под соответствующим комментарием. Комментарий не стирать.
module data_path(x, y, s, b, y_select_next, s_step, y_en, s_en, y_store_x, s_add, s_zero, clk, rst , s_is_zero);
  input [7:0] x;
  input [1:0] y_select_next, s_step;
  input clk, rst, y_en, s_en, y_store_x, s_add, s_zero;
  output reg [7:0] y;
  output reg [2:0] s;
  output b;
  
  /* ОБЪЯВЛЕНИЯ НОВЫХ УПРАВЛЯЮЩИХ ПОРТОВ И НОВЫХ ВНУТРЕННИХ ТОЧЕК */
  output s_is_zero;
  
  
  
  wire [7:0] y_in;
  reg [7:0] y_next;
  wire [2:0] s_in, s_base;
  
  // регистр для y
  always @(posedge clk, posedge rst)
    if(rst) y <= 0;
    else
      if(y_en) y <= y_in;
  
  // регистр для s
  always @(posedge clk, posedge rst)
    if(rst) s <= 0;
    else
      if(s_en) s <= s_in;
  
  // селектор для b
  assign b = y[s];
  
  // ближний мультиплексор на входе регистра y
  assign y_in = y_store_x ? x : y_next;
  
  // дальний мультиплексор на входе регистра y
  always @*
  begin
    y_next = 1'bx;
    case(y_select_next)
    2'd0 : y_next = y;
    2'd1 : y_next = y + 1;
    2'd2 : y_next = y + s;
    2'd3 : y_next = y - s;
    endcase
  end
  
  // мультиплексор на входе s
  assign s_in = s_add ? s_base + s_step : s_base - s_step;
  
  // мультиплексор, выбирающий первое слагаемое для нового значения s
  assign s_base = s_zero ? 0 : s;
  
  /* РЕАЛИЗАЦИЯ ПОДСХЕМ ДЛЯ ПРЕОБРАЗОВАНИЯ ДАННЫХ В УПРАВЛЕНИЕ */
  
  assign s_is_zero = (s==0);
  
endmodule

task4/main.v
// Новые точки объявлять перед экземплярами под соответствующим комментарием. Комментарий не стирать.
// Назначать новые порты в экземплярах - в конце всех назначений под соответствующим комментарием. Комментарий не стирать.
// НЕ ЗАБУДЬТЕ поставить запятую после ".rst(rst)", если добавляете новые порты.
module main(x, y, s, b, on, start, regime, active, clk, rst);
  input [7:0] x;
  input [1:0] on;
  input start;
  input clk, rst;
  output [7:0] y;
  output [2:0] s;
  output b, active;
  output [1:0] regime;
  
  wire [1:0] y_select_next, s_step;
  wire y_en, s_en, y_store_x, s_add, s_zero;
  
  /* ОБЪЯВЛЕНИЯ ТОЧЕК */
  wire s_is_zero;
  
  data_path _data_path(
    // данные
    .x(x),
    .y(y),
    .s(s),
    .b(b),
    // исходное управление
    .y_select_next(y_select_next),
    .s_step(s_step),
    .y_en(y_en),
    .s_en(s_en),
    .y_store_x(y_store_x),
    .s_add(s_add),
    .s_zero(s_zero),
    // такт и сброс
    .clk(clk),
    .rst(rst),
    /* ДОБАВЛЕННЫЕ ПОРТЫ */
    .s_is_zero(s_is_zero)
  );
  control_path _control_path(
    // подключения к портам схемы
    .on(on),
    .start(start),
    .regime(regime),
    .active(active),
    // подключения к портам операционного автомата
    .y_select_next(y_select_next),
    .s_step(s_step),
    .y_en(y_en),
    .s_en(s_en),
    .y_store_x(y_store_x),
    .s_add(s_add),
    .s_zero(s_zero),
    // такт и сброс
    .clk(clk),
    .rst(rst),
    /* ДОБАВЛЕННЫЕ ПОРТЫ */
    .s_is_zero(s_is_zero)
  );
endmodule

task4/testbanch.v

module testbanch();
  reg [7:0] x;
  reg [1:0] on;
  reg start;
  reg clk, rst;
  wire [7:0] y;
  wire [2:0] s;
  wire b, active;
  wire [1:0] regime;
  
  wire [1:0] y_select_next, s_step;
  wire y_en, s_en, y_store_x, s_add, s_zero;
  
  reg test_valid;
  
  initial clk = 0;
  initial rst = 1;
  initial #2 rst = 0;
  
  initial #100 $finish;
  always #1 clk = !clk;
  
  main aaa(.x(x), .y(y), .s(s), .b(b), .on(on), .start(start), .regime(regime), .active(active), .clk(clk), .rst(rst));
  
  initial begin
    $dumpfile("test.vcd");
		$dumpvars;
    
    // тест для Режмима счёта 0~32 
    on = 2;
    #4 start = 1;
    on=0;
    #20 start = 0;
    #8 ;
    // тест Режима обновления 32~40
    x = 57;
    on = 3;
    #8 
    // тест Режима перечисления 40~80
    on=1;
    #4 start = 1;on = 0;
    #32 ;
    //тест выключенного режима 80~100
    
    
    
  end
  
  
  
endmodule

task4/test.vcd
$date
	Mon Dec  2 20:28:03 2019
$end
$version
	Icarus Verilog
$end
$timescale
	1s
$end
$scope module testbanch $end
$var wire 8 ! y [7:0] $end
$var wire 3 " s [2:0] $end
$var wire 2 # regime [1:0] $end
$var wire 1 $ b $end
$var wire 1 % active $end
$var reg 1 & clk $end
$var reg 2 ' on [1:0] $end
$var reg 1 ( rst $end
$var reg 1 ) start $end
$var reg 8 * x [7:0] $end
$scope module aaa $end
$var wire 1 & clk $end
$var wire 2 + on [1:0] $end
$var wire 1 ( rst $end
$var wire 1 ) start $end
$var wire 8 , x [7:0] $end
$var wire 1 - y_store_x $end
$var wire 2 . y_select_next [1:0] $end
$var wire 1 / y_en $end
$var wire 8 0 y [7:0] $end
$var wire 1 1 s_zero $end
$var wire 2 2 s_step [1:0] $end
$var wire 1 3 s_is_zero $end
$var wire 1 4 s_en $end
$var wire 1 5 s_add $end
$var wire 3 6 s [2:0] $end
$var wire 2 7 regime [1:0] $end
$var wire 1 $ b $end
$var wire 1 % active $end
$scope module _control_path $end
$var wire 1 & clk $end
$var wire 2 8 on [1:0] $end
$var wire 1 ( rst $end
$var wire 1 ) start $end
$var wire 1 3 s_is_zero $end
$var wire 1 9 refresh_off $end
$var wire 1 : enum_off $end
$var reg 1 % active $end
$var reg 5 ; counter16 [4:0] $end
$var reg 2 < counter3 [1:0] $end
$var reg 3 = next_state [2:0] $end
$var reg 2 > regime [1:0] $end
$var reg 1 5 s_add $end
$var reg 1 4 s_en $end
$var reg 2 ? s_step [1:0] $end
$var reg 1 1 s_zero $end
$var reg 3 @ state [2:0] $end
$var reg 1 / y_en $end
$var reg 2 A y_select_next [1:0] $end
$var reg 1 - y_store_x $end
$upscope $end
$scope module _data_path $end
$var wire 1 & clk $end
$var wire 1 ( rst $end
$var wire 1 5 s_add $end
$var wire 1 4 s_en $end
$var wire 2 B s_step [1:0] $end
$var wire 1 1 s_zero $end
$var wire 8 C x [7:0] $end
$var wire 1 / y_en $end
$var wire 2 D y_select_next [1:0] $end
$var wire 1 - y_store_x $end
$var wire 8 E y_in [7:0] $end
$var wire 1 3 s_is_zero $end
$var wire 3 F s_in [2:0] $end
$var wire 3 G s_base [2:0] $end
$var wire 1 $ b $end
$var reg 3 H s [2:0] $end
$var reg 8 I y [7:0] $end
$var reg 8 J y_next [7:0] $end
$upscope $end
$upscope $end
$upscope $end
$enddefinitions $end
#0
$dumpvars
b0x J
b0 I
b0 H
b0 G
bx F
bx E
bx D
bx C
bx B
bx A
b0 @
bx ?
b0 >
b11 =
bx <
bx ;
x:
x9
b10 8
b0 7
b0 6
x5
04
13
bx 2
x1
b0 0
0/
bx .
x-
bx ,
b10 +
bx *
x)
1(
b10 '
0&
0%
0$
b0 #
b0 "
b0 !
$end
#1
b11 =
0:
b10000 ;
09
b10 <
1&
#2
0&
0(
#3
0%
b10 #
b10 7
b10 >
b0 =
b11 @
1&
#4
b1 J
b111 F
b1 E
b1 .
b1 A
b1 D
1/
01
05
14
b1 2
b1 ?
b1 B
0-
b11 =
0&
b0 '
b0 +
b0 8
1)
#5
b110 F
b10 E
b111 G
0/
b10 J
03
b111 "
b111 6
b111 H
0$
b1 !
b1 0
b1 I
1&
#6
0&
#7
b101 F
b10 J
b110 G
b110 "
b110 6
b110 H
1&
#8
0&
#9
b100 F
b10 J
b101 G
b101 "
b101 6
b101 H
1&
#10
0&
#11
b11 F
b10 J
b100 G
b100 "
b100 6
b100 H
1&
#12
0&
#13
b10 F
b10 J
b11 G
b11 "
b11 6
b11 H
1&
#14
0&
#15
b1 F
b10 J
b10 G
b10 "
b10 6
b10 H
1&
#16
0&
#17
b0 F
b10 J
b1 G
b1 "
b1 6
b1 H
1&
#18
0&
#19
b111 F
b10 J
b0 G
1/
1$
13
b0 "
b0 6
b0 H
1&
#20
0&
#21
b110 F
b11 E
b111 G
0/
b11 J
03
b111 "
b111 6
b111 H
0$
b10 !
b10 0
b10 I
1&
#22
0&
#23
b101 F
b11 J
b110 G
b110 "
b110 6
b110 H
1&
#24
04
b0 =
0&
0)
#25
0%
b0 #
b0 7
b0 >
b0 =
b0 @
1&
#26
0&
#27
1&
#28
0&
#29
1&
#30
0&
#31
1&
#32
b100 =
0&
b11 '
b11 +
b11 8
b111001 *
b111001 ,
b111001 C
#33
b111001 E
1-
1/
0%
b11 #
b11 7
b11 >
b100 =
b100 @
1&
#34
0&
#35
b110011 E
b111 F
b11 .
b11 A
b11 D
0-
15
14
b110011 J
b1 <
b111001 !
b111001 0
b111001 I
1&
#36
0&
#37
b0 F
b101100 E
04
0/
b0 =
b111 G
b101100 J
19
b0 <
b111 "
b111 6
b111 H
b110011 !
b110011 0
b110011 I
1&
#38
0&
#39
0%
b0 #
b0 7
b0 >
b100 =
09
b11 <
b0 @
1&
#40
b1 =
0&
b1 '
b1 +
b1 8
#41
0%
b1 #
b1 7
b1 >
b1 =
b10 <
b1 @
1&
#42
0&
#43
1&
#44
b10 =
0&
b0 '
b0 +
b0 8
1)
#45
b1 F
b0 G
14
11
1%
b1 #
b1 7
b1 >
b10 =
b10 @
1&
#46
0&
#47
b110010 E
04
b110010 J
b1111 ;
1$
b1 "
b1 6
b1 H
1&
#48
0&
#49
b1110 ;
1&
#50
0&
#51
b1101 ;
1&
#52
0&
#53
b1 G
b11 F
01
b10 2
b10 ?
b10 B
14
b1100 ;
1&
#54
0&
#55
b110000 E
b101 F
04
b110000 J
b11 G
b1011 ;
0$
b11 "
b11 6
b11 H
1&
#56
0&
#57
b1010 ;
1&
#58
0&
#59
b1001 ;
1&
#60
0&
#61
14
b1000 ;
1&
#62
0&
#63
b101110 E
b111 F
04
b101110 J
b101 G
b111 ;
1$
b101 "
b101 6
b101 H
1&
#64
0&
#65
b110 ;
1&
#66
0&
#67
b101 ;
1&
#68
0&
#69
14
b100 ;
1&
#70
0&
#71
b101100 E
b1 F
04
b101100 J
b111 G
b11 ;
0$
b111 "
b111 6
b111 H
1&
#72
0&
#73
b10 ;
1&
#74
0&
#75
b1 ;
1&
#76
0&
#77
b0 G
b1 2
b1 ?
b1 B
11
14
b0 =
1:
b0 ;
1&
#78
0&
#79
b110010 E
b110010 J
0%
b0 #
b0 7
b0 >
04
b0 =
0:
b11111 ;
1$
b1 "
b1 6
b1 H
b0 @
1&
#80
0&
#81
b10000 ;
1&
